ez_life/__init__.py
ez_life/jt_property.py
ez_life/param2attr.py
ez_life_package/__init__.py
ez_life_package/jt_property.py
ez_life_package/param2attr.py
ez_life-1.1.0.dist-info/LICENSE
ez_life-1.1.0.dist-info/METADATA
ez_life-1.1.0.dist-info/WHEEL
ez_life-1.1.0.dist-info/top_level.txt
ez_life-1.1.0.dist-info/RECORD
