Metadata-Version: 2.1
Name: ez-life
Version: 1.1.0
Summary: A Python Package to make life ez for pythonistas
Home-page: https://github.com/Josiah-tan/ez_life
Author: Josiah Tan
Author-email: josiah123t@gmail.com
License: MIT
Platform: UNKNOWN
Classifier: License :: OSI Approved :: MIT License
Classifier: Programming Language :: Python :: 3
Classifier: Programming Language :: Python :: 3.6
Classifier: Programming Language :: Python :: 3.7
Classifier: Programming Language :: Python :: 3.8
Classifier: Programming Language :: Python :: 3.9
